nmdc_geoloc_tools/__init__.py
nmdc_geoloc_tools/data/ENVO_Landuse_Systems_lookup.csv
nmdc_geoloc_tools/data/ENVO_Landuse_lookup.csv
nmdc_geoloc_tools/data/README.md
nmdc_geoloc_tools/data/zobler_540_MixS_lookup.csv
nmdc_geoloc_tools/geotools.py
nmdc_geoloc_tools-0.2.1.dist-info/METADATA
nmdc_geoloc_tools-0.2.1.dist-info/WHEEL
nmdc_geoloc_tools-0.2.1.dist-info/RECORD
